flyonthewall/__init__.py
flyonthewall/flyonthewall.py
flyonthewall-0.1a12.dist-info/METADATA
flyonthewall-0.1a12.dist-info/RECORD
flyonthewall-0.1a12.dist-info/WHEEL
flyonthewall-0.1a12.dist-info/top_level.txt
