Metadata-Version: 2.1
Name: flyonthewall
Version: 0.1a12
Summary: Forum scraper that returns relevant posts and attachments based on keywords provided as argument or in file.
Home-page: https://github.com/hmallen/flyonthewall
Author: Hunter M. Allen
Author-email: allenhm@gmail.com
License: MIT
Keywords: forum,scrape
Platform: UNKNOWN
Classifier: Programming Language :: Python :: 3
Classifier: License :: OSI Approved :: MIT License
Classifier: Operating System :: OS Independent
Requires-Dist: boto3 (>=1.7.25)
Requires-Dist: beautifulsoup4 (>=4.6.0)
Requires-Dist: requests (>=2.13.0)
Requires-Dist: slackclient (>=1.2.1)
Requires-Dist: wget (>=3.2)
